sceua/__init__.py
sceua/sceua.py
sceua-0.1.0.dist-info/METADATA
sceua-0.1.0.dist-info/WHEEL
sceua-0.1.0.dist-info/licenses/AUTHORS.md
sceua-0.1.0.dist-info/licenses/LICENSE
sceua-0.1.0.dist-info/RECORD
