Metadata-Version: 2.4
Name: sceua
Version: 0.1.0
Summary: Parameter calibration using Shuffle Complex Evolution algorithm.
Project-URL: Changelog, https://sceua.readthedocs.io/en/latest/CHANGELOG
Project-URL: CI, https://github.com/cheginit/sceua/actions
Project-URL: Homepage, https://sceua.readthedocs.io
Project-URL: Issues, https://github.com/cheginit/sceua/issues
Author-email: Taher Chegini <cheginit@gmail.com>
License: MIT
License-File: AUTHORS.md
License-File: LICENSE
Classifier: Development Status :: 4 - Beta
Classifier: Intended Audience :: Science/Research
Classifier: License :: OSI Approved :: MIT License
Classifier: Operating System :: OS Independent
Classifier: Programming Language :: Python
Classifier: Programming Language :: Python :: 3 :: Only
Classifier: Programming Language :: Python :: 3.10
Classifier: Programming Language :: Python :: 3.11
Classifier: Programming Language :: Python :: 3.12
Classifier: Programming Language :: Python :: 3.13
Classifier: Topic :: Scientific/Engineering
Classifier: Topic :: Scientific/Engineering :: GIS
Classifier: Typing :: Typed
Requires-Python: >=3.10
Requires-Dist: numpy>=2
Requires-Dist: scipy>=1.15
Provides-Extra: benchmark
Requires-Dist: landscapes; extra == 'benchmark'
Requires-Dist: numba; extra == 'benchmark'
Requires-Dist: numpy; extra == 'benchmark'
Requires-Dist: pandas; extra == 'benchmark'
Requires-Dist: pytest-codspeed; extra == 'benchmark'
Provides-Extra: dev
Requires-Dist: folium; extra == 'dev'
Requires-Dist: geopandas>=1; extra == 'dev'
Requires-Dist: hydrosignatures; extra == 'dev'
Requires-Dist: ipykernel; extra == 'dev'
Requires-Dist: ipywidgets; extra == 'dev'
Requires-Dist: landscapes; extra == 'dev'
Requires-Dist: mapclassify; extra == 'dev'
Requires-Dist: matplotlib; extra == 'dev'
Requires-Dist: netcdf4; extra == 'dev'
Requires-Dist: numba; extra == 'dev'
Requires-Dist: pandas>=2; extra == 'dev'
Requires-Dist: pytest; extra == 'dev'
Requires-Dist: rioxarray; extra == 'dev'
Requires-Dist: xarray; extra == 'dev'
Provides-Extra: docs
Requires-Dist: black; extra == 'docs'
Requires-Dist: mkdocs; extra == 'docs'
Requires-Dist: mkdocs-jupyter; extra == 'docs'
Requires-Dist: mkdocs-material; extra == 'docs'
Requires-Dist: mkdocstrings-python; extra == 'docs'
Provides-Extra: lint
Requires-Dist: codespell; extra == 'lint'
Requires-Dist: pre-commit; extra == 'lint'
Provides-Extra: test
Requires-Dist: landscapes; extra == 'test'
Requires-Dist: numba; extra == 'test'
Requires-Dist: numpy; extra == 'test'
Requires-Dist: pandas; extra == 'test'
Requires-Dist: pytest-cov; extra == 'test'
Requires-Dist: pytest-sugar; extra == 'test'
Provides-Extra: typecheck
Requires-Dist: pyright; extra == 'typecheck'
